krakenpy/__init__.py
krakenpy/exceptions.py
krakenpy/payloads.py
krakenpy/response.py
krakenpy/service.py
krakenpy/utils.py
krakenpy-0.1.4.dist-info/METADATA
krakenpy-0.1.4.dist-info/WHEEL
krakenpy-0.1.4.dist-info/RECORD
