Metadata-Version: 2.1
Name: krakenpy
Version: 0.1.4
Summary: krakenpy is tool in which we integrated kraken crypto exchange API
Home-page: https://github.com/Sheikhharis50/krakenpy
Keywords: kraken,kraken-api,python,crypto
Author: Sheikh Haris Zahid
Requires-Python: >=3.10,<4.0
Classifier: Development Status :: 1 - Planning
Classifier: Intended Audience :: Developers
Classifier: License :: OSI Approved :: MIT License
Classifier: Operating System :: MacOS
Classifier: Programming Language :: Python :: 3
Classifier: Programming Language :: Python :: 3.10
Classifier: Programming Language :: Python :: 3.11
Classifier: Programming Language :: Python :: 3.10
Requires-Dist: krakenex (>=2.1.0,<3.0.0)
Project-URL: Repository, https://github.com/Sheikhharis50/krakenpy
